falconpunch-1.0.dist-info/METADATA
falconpunch-1.0.dist-info/WHEEL
falconpunch-1.0.dist-info/licenses/LICENSE
falconpunch/__init__.py
falconpunch/falconpunch.cpython-312-aarch64-linux-gnu.so
falconpunch-1.0.dist-info/RECORD
