Metadata-Version: 2.3
Name: falconpunch
Version: 1.0
Classifier: Programming Language :: Rust
Classifier: Programming Language :: Python :: Implementation :: CPython
Classifier: Programming Language :: Python :: Implementation :: PyPy
License-File: LICENSE
Summary: Rust bindings for Overpunch parsing/formatting
Keywords: overpunch,cobol,ibm,mainframe
Author: Roman Sorin <romansorin@cap-rx.com>
Author-email: Roman Sorin <romansorin@cap-rx.com>
License: MIT
Requires-Python: >=3.12
